{
  "business": {
    "name": "Dharmaji Textile",
    "full_address": "Block 164-173, 193, New Cloth Market, Sarangpur, Sherkotda, Ahmedabad, Gujarat 380002, India",
    "phone": "+91 79 2216 3816",
    "local_phone": "079 2216 3816",
    "website": "http://dharmaji.com/home/",
    "rating": 4.6,
    "total_reviews": 9,
    "business_status": "OPERATIONAL",
    "google_maps_url": "https://maps.google.com/?cid=1925747730230282356",
    "lat": 23.0179597,
    "lng": 72.5998611,
    "open_now": true,
    "weekday_hours": [
      "Monday: 10:00 AM – 8:00 PM",
      "Tuesday: 10:00 AM – 8:00 PM",
      "Wednesday: 10:00 AM – 8:00 PM",
      "Thursday: 10:00 AM – 8:00 PM",
      "Friday: 10:00 AM – 8:00 AM",
      "Saturday: 10:00 AM – 8:00 PM",
      "Sunday: Closed"
    ],
    "types": [
      "establishment",
      "point_of_interest",
      "store"
    ],
    "reviews": [
      {
        "author_name": "Priyanka Sharma",
        "rating": 1,
        "review": "I am not satisfied with there srvice they didn't send my order on meesho show that they send but after that I got failed delivery order because of out of stock",
        "time_ago": "8 months ago"
      },
      {
        "author_name": "venkat dvr",
        "rating": 5,
        "review": "Nice place",
        "time_ago": "4 years ago"
      },
      {
        "author_name": "Sandhi Yasin",
        "rating": 5,
        "time_ago": "6 months ago"
      }
    ],
    "photos": [
      {
        "width": 1080,
        "height": 2880,
        "photo_url": "https://test-cloudvault.s3.ap-south-1.amazonaws.com/dharmaji1.jpg"
      },
      {
        "width": 653,
        "height": 986,
        "photo_url": "https://test-cloudvault.s3.ap-south-1.amazonaws.com/dharmaji2.jpg"
      },
      {
        "width": 1280,
        "height": 720,
        "photo_url": "https://test-cloudvault.s3.ap-south-1.amazonaws.com/dharmaji3.jpg"
      },
      {
        "width": 1280,
        "height": 720,
        "photo_url": "https://test-cloudvault.s3.ap-south-1.amazonaws.com/dharmaji4.jpg"
      }
    ],
    "main_photo_url": "https://test-cloudvault.s3.ap-south-1.amazonaws.com/dharmaji1.jpg"
  },
  "website_config": {
    "theme": "luxury-fashion",
    "navbarVariant": "transparent-floating",
    "footerVariant": "editorial-footer",
    "branding": {
      "style": "elegant",
      "tone": "sophisticated"
    },
    "layout": {
      "sections": [
        {
          "type": "Hero",
          "variant": "luxury-parallax"
        },
        {
          "type": "About",
          "variant": "luxury-narrative"
        },
        {
          "type": "Gallery",
          "variant": "editorial-grid"
        },
        {
          "type": "Reviews",
          "variant": "editorial-quotes"
        },
        {
          "type": "Contact",
          "variant": "minimal-contact"
        }
      ]
    }
  },
  "website_content": {
    "hero": {
      "title": "Redefining Textiles, Crafting Legacies.",
      "subtitle": "Experience the unparalleled quality and artistry of Dharmaji Textile, where tradition meets modern luxury.",
      "primaryButton": "Explore Collections",
      "secondaryButton": "Discover Our Story"
    },
    "about": {
      "title": "Our Heritage of Excellence",
      "description": "Dharmaji Textile stands as a beacon of textile innovation and timeless craftsmanship. We meticulously source and create exceptional fabrics, embodying a commitment to quality and elegance that defines luxury."
    },
    "gallery": {
      "title": "A Vision in Fabric",
      "description": "Immerse yourself in our curated selection of exquisite textiles. Each piece tells a story of meticulous design and unparalleled texture, waiting to inspire your next creation."
    },
    "reviews": {
      "title": "Voices of Our Valued Partners",
      "description": "Our commitment to excellence is reflected in the satisfaction of those who choose Dharmaji Textile. Discover why we are the preferred choice for discerning designers and brands."
    },
    "contact": {
      "title": "Connect With Our Team",
      "description": "For bespoke inquiries, collaborations, or further information on our premium textile offerings, please reach out. We look forward to assisting you.",
      "buttonText": "Send an Inquiry"
    }
  }
}
